pydisconet/0.parse.sh
pydisconet/__init__.py
pydisconet/input.yaml
pydisconet/requirements.txt
pydisconet/test.py
pydisconet/analyze/__init__.py
pydisconet/analyze/analyze_helpers.py
pydisconet/analyze/embed_datasets.py
pydisconet/analyze/network_statistics.py
pydisconet/analyze/run_gat.py
pydisconet/analyze/run_zeroshot.py
pydisconet/database_parser/__init__.py
pydisconet/database_parser/download_arxiv.py
pydisconet/database_parser/download_openalex.py
pydisconet/database_parser/process_arxiv.py
pydisconet/database_parser/process_combine_years.py
pydisconet/database_parser/process_openalex.py
pydisconet/interpreter/__init__.py
pydisconet/interpreter/input_handler.py
pydisconet/interpreter/run_jobs.py
pydisconet/interpreter/sbatch_writer.py
pydisconet/interpreter/steps_parser.py
pydisconet/notebooks/5_plots.ipynb
pydisconet/notebooks/main.ipynb
pydisconet/notebooks/to_test.ipynb
pydisconet/plotter/__init__.py
pydisconet/plotter/compile_auc_aupr.py
pydisconet/plotter/compile_tfidf.py
pydisconet/plotter/model_histograms.py
pydisconet/plotter/plotter_helper.py
pydisconet/preprocessing/__init__.py
pydisconet/preprocessing/preprocess_data_for_embedding.py
pydisconet/preprocessing/preprocess_data_for_model.py
pydisconet/scripts/0.1.py
pydisconet/scripts/1_data_downloading.py
pydisconet/scripts/2_embedding_datasets.py
pydisconet/scripts/3_preparing_objects_network.py
pydisconet/scripts/4.1_zeroshot.py
pydisconet/scripts/4.2_gat_gat_embed.py
pydisconet/scripts/5_plotting.py
pydisconet/scripts/model_histograms.py
pydisconet/scripts/setup_logging.py
pydisconet/scripts/version.py
pydisconet/utils/__init__.py
pydisconet/utils/utility.py
pydisconet-0.2.1.dist-info/LICENSE
pydisconet-0.2.1.dist-info/METADATA
pydisconet-0.2.1.dist-info/WHEEL
pydisconet-0.2.1.dist-info/top_level.txt
pydisconet-0.2.1.dist-info/RECORD
