Metadata-Version: 2.1
Name: pydisconet
Version: 0.2.1
Summary: analyzing the co-authorship network of researchers in the field of biology
Home-page: https://github.com/swapnilkeshari/disconet
Author: Swapnil Keshari**, Zarifeh Heidari, Akash Kishore, Jishnu Das
Author-email: swk25@pitt.edu
License: MIT license
Keywords: co-authorship,ML,AI,network analysis,graph theory,biology,bioinformatics
Classifier: Development Status :: 3 - Alpha
Classifier: Intended Audience :: Developers
Classifier: Topic :: Software Development :: Build Tools
Classifier: Programming Language :: Python :: 3.10
Requires-Python: >=3.8
License-File: LICENSE
Requires-Dist: absl-py==2.1.0
Requires-Dist: abydos==0.5.0
Requires-Dist: aiohttp==3.9.1
Requires-Dist: aiosignal==1.3.1
Requires-Dist: annotated-types==0.6.0
Requires-Dist: anyio==4.2.0
Requires-Dist: argon2-cffi==23.1.0
Requires-Dist: argon2-cffi-bindings==21.2.0
Requires-Dist: arrow==1.3.0
Requires-Dist: asttokens==2.4.1
Requires-Dist: astunparse==1.6.3
Requires-Dist: async-lru==2.0.4
Requires-Dist: async-timeout==4.0.3
Requires-Dist: attrs==23.1.0
Requires-Dist: Babel==2.14.0
Requires-Dist: backcall==0.2.0
Requires-Dist: beautifulsoup4==4.12.2
Requires-Dist: bio
Requires-Dist: biopython==1.83
Requires-Dist: biothings-client==0.3.1
Requires-Dist: bleach==6.1.0
Requires-Dist: blis==0.7.11
Requires-Dist: bokeh==3.3.2
Requires-Dist: build==1.2.1
Requires-Dist: catalogue==2.0.10
Requires-Dist: certifi==2023.11.17
Requires-Dist: cffi==1.16.0
Requires-Dist: chardet==5.2.0
Requires-Dist: charset-normalizer==3.3.2
Requires-Dist: click==8.1.7
Requires-Dist: cloudpathlib==0.16.0
Requires-Dist: cloudpickle==3.0.0
Requires-Dist: comm==0.2.0
Requires-Dist: confection==0.1.4
Requires-Dist: contourpy==1.2.0
Requires-Dist: cryptography==41.0.7
Requires-Dist: cycler==0.12.1
Requires-Dist: cymem==2.0.8
Requires-Dist: dask==2023.12.1
Requires-Dist: dask-jobqueue==0.8.2
Requires-Dist: dask-mpi==2022.4.0
Requires-Dist: dask-yarn==0.9
Requires-Dist: dask-labextension==7.0.0
Requires-Dist: datasets==2.16.1
Requires-Dist: debugpy==1.8.0
Requires-Dist: decorator==5.1.1
Requires-Dist: defusedxml==0.7.1
Requires-Dist: deprecation==2.1.0
Requires-Dist: dill==0.3.7
Requires-Dist: distributed==2023.12.1
Requires-Dist: docopt==0.6.2
Requires-Dist: duckdb==0.10.1
Requires-Dist: et-xmlfile==1.1.0
Requires-Dist: exceptiongroup==1.2.0
Requires-Dist: executing==2.0.1
Requires-Dist: fastjsonschema==2.19.0
Requires-Dist: filelock==3.9.0
Requires-Dist: flatbuffers==24.3.25
Requires-Dist: fonttools==4.49.0
Requires-Dist: fqdn==1.5.1
Requires-Dist: frozenlist==1.4.1
Requires-Dist: fsspec==2023.10.0
Requires-Dist: fuzzywuzzy==0.18.0
Requires-Dist: gast==0.5.4
Requires-Dist: google-pasta==0.2.0
Requires-Dist: gprofiler-official==1.0.0
Requires-Dist: graphviz==0.20.1
Requires-Dist: grpcio==1.60.0
Requires-Dist: h5py==3.11.0
Requires-Dist: hmni==0.1.8
Requires-Dist: huggingface-hub==0.20.1
Requires-Dist: idna==3.6
Requires-Dist: ijson==3.2.3
Requires-Dist: importlib-metadata==7.0.1
Requires-Dist: ipykernel==6.27.1
Requires-Dist: ipython==8.12.3
Requires-Dist: ipywidgets==8.1.1
Requires-Dist: isoduration==20.11.0
Requires-Dist: jedi==0.19.1
Requires-Dist: Jinja2==3.1.2
Requires-Dist: joblib==1.3.2
Requires-Dist: json5==0.9.14
Requires-Dist: jsonpointer==2.4
Requires-Dist: jsonschema==4.20.0
Requires-Dist: jsonschema-specifications==2023.12.1
Requires-Dist: jupyter-events==0.9.0
Requires-Dist: jupyter-lsp==2.2.1
Requires-Dist: jupyter-client==8.6.0
Requires-Dist: jupyter-core==5.5.1
Requires-Dist: jupyter-server==2.12.1
Requires-Dist: jupyter-server-proxy==4.1.0
Requires-Dist: jupyter-server-terminals==0.5.0
Requires-Dist: jupyterlab-widgets==3.0.9
Requires-Dist: jupyterlab-pygments==0.3.0
Requires-Dist: jupyterlab-server==2.25.2
Requires-Dist: kaggle==1.6.12
Requires-Dist: kiwisolver==1.4.5
Requires-Dist: langcodes==3.4.0
Requires-Dist: language-data==1.2.0
Requires-Dist: libclang==18.1.1
Requires-Dist: llvmlite==0.41.1
Requires-Dist: locket==1.0.0
Requires-Dist: marisa-trie==1.1.0
Requires-Dist: Markdown==3.6
Requires-Dist: markdown-it-py==3.0.0
Requires-Dist: MarkupSafe==2.1.3
Requires-Dist: matplotlib==3.8.3
Requires-Dist: matplotlib-inline==0.1.6
Requires-Dist: matplotlib-label-lines==0.7.0
Requires-Dist: mdurl==0.1.2
Requires-Dist: mistune==3.0.2
Requires-Dist: ml-dtypes==0.3.2
Requires-Dist: more-itertools==10.2.0
Requires-Dist: mpmath==1.3.0
Requires-Dist: msgpack==1.0.7
Requires-Dist: multidict==6.0.4
Requires-Dist: multiprocess==0.70.15
Requires-Dist: murmurhash==1.0.10
Requires-Dist: mygene==3.2.2
Requires-Dist: namex==0.0.7
Requires-Dist: nbclient==0.9.0
Requires-Dist: nbconvert==7.13.1
Requires-Dist: nbformat==5.9.2
Requires-Dist: nest-asyncio==1.5.8
Requires-Dist: networkit==11.0
Requires-Dist: networkx==3.0
Requires-Dist: nh3==0.2.17
Requires-Dist: nltk==3.8.1
Requires-Dist: notebook-shim==0.2.3
Requires-Dist: numba==0.58.1
Requires-Dist: numpy==1.26.2
Requires-Dist: openpyxl==3.1.2
Requires-Dist: opt-einsum==3.3.0
Requires-Dist: optree==0.11.0
Requires-Dist: overrides==7.4.0
Requires-Dist: packaging==23.2
Requires-Dist: pandas==2.1.4
Requires-Dist: pandocfilters==1.5.0
Requires-Dist: parso==0.8.3
Requires-Dist: partd==1.4.1
Requires-Dist: pexpect==4.9.0
Requires-Dist: pickleshare==0.7.5
Requires-Dist: Pillow==10.1.0
Requires-Dist: pipreqs==0.5.0
Requires-Dist: platformdirs==4.1.0
Requires-Dist: pooch==1.8.1
Requires-Dist: preshed==3.0.9
Requires-Dist: prometheus-client==0.19.0
Requires-Dist: prompt-toolkit==3.0.43
Requires-Dist: protobuf==4.25.1
Requires-Dist: psutil==5.9.7
Requires-Dist: ptyprocess==0.7.0
Requires-Dist: pure-eval==0.2.2
Requires-Dist: py4j==0.10.9.7
Requires-Dist: pyarrow==14.0.2
Requires-Dist: pyarrow-hotfix==0.6
Requires-Dist: pycparser==2.21
Requires-Dist: pydantic==2.7.1
Requires-Dist: pydantic-core==2.18.2
Requires-Dist: Pygments==2.18.0
Requires-Dist: pynndescent==0.5.11
Requires-Dist: pyparsing==3.1.1
Requires-Dist: pyproject-hooks==1.1.0
Requires-Dist: pyspark==3.5.1
Requires-Dist: python-dateutil==2.8.2
Requires-Dist: python-json-logger==2.0.7
Requires-Dist: python-slugify==8.0.4
Requires-Dist: pytz==2023.3.post1
Requires-Dist: PyYAML==6.0.1
Requires-Dist: pyzmq==25.1.2
Requires-Dist: rapidfuzz==3.9.0
Requires-Dist: rapidgzip==0.11.1
Requires-Dist: readme-renderer==43.0
Requires-Dist: referencing==0.32.0
Requires-Dist: regex==2023.12.25
Requires-Dist: requests==2.31.0
Requires-Dist: requests-toolbelt==1.0.0
Requires-Dist: rfc3339-validator==0.1.4
Requires-Dist: rfc3986==2.0.0
Requires-Dist: rfc3986-validator==0.1.1
Requires-Dist: rich==13.7.1
Requires-Dist: rpds-py==0.15.2
Requires-Dist: safetensors==0.4.1
Requires-Dist: scikit-learn==1.3.2
Requires-Dist: scipy==1.11.4
Requires-Dist: seaborn==0.13.2
Requires-Dist: Send2Trash==1.8.2
Requires-Dist: sentence-transformers==2.2.2
Requires-Dist: sentencepiece==0.1.99
Requires-Dist: simpervisor==1.0.0
Requires-Dist: six==1.16.0
Requires-Dist: skein==0.8.2
Requires-Dist: smart-open==6.4.0
Requires-Dist: sniffio==1.3.0
Requires-Dist: sortedcontainers==2.4.0
Requires-Dist: soupsieve==2.5
Requires-Dist: spacy==3.7.4
Requires-Dist: spacy-legacy==3.0.12
Requires-Dist: spacy-loggers==1.0.5
Requires-Dist: srsly==2.4.8
Requires-Dist: stack-data==0.6.3
Requires-Dist: sympy==1.12
Requires-Dist: tblib==3.0.0
Requires-Dist: tensorboard==2.16.2
Requires-Dist: tensorboard-data-server==0.7.2
Requires-Dist: tensorflow-io-gcs-filesystem==0.36.0
Requires-Dist: termcolor==2.4.0
Requires-Dist: terminado==0.18.0
Requires-Dist: text-unidecode==1.3
Requires-Dist: thefuzz==0.22.1
Requires-Dist: thinc==8.2.3
Requires-Dist: threadpoolctl==3.2.0
Requires-Dist: tinycss2==1.2.1
Requires-Dist: tokenizers==0.15.0
Requires-Dist: tomli==2.0.1
Requires-Dist: toolz==0.12.0
Requires-Dist: torch==2.1.2
Requires-Dist: torchaudio==2.1.2
Requires-Dist: torchvision==0.16.2
Requires-Dist: torch-geometric==2.4.0
Requires-Dist: tornado==6.4
Requires-Dist: tqdm==4.66.1
Requires-Dist: traitlets==5.14.0
Requires-Dist: transformers==4.36.2
Requires-Dist: triton==2.1.0
Requires-Dist: typer==0.9.4
Requires-Dist: types-python-dateutil==2.8.19.14
Requires-Dist: typing-extensions==4.11.0
Requires-Dist: tzdata==2023.4
Requires-Dist: umap-learn==0.5.5
Requires-Dist: Unidecode==1.3.8
Requires-Dist: uri-template==1.3.0
Requires-Dist: urllib3==2.1.0
Requires-Dist: wasabi==1.1.2
Requires-Dist: wcwidth==0.2.12
Requires-Dist: weasel==0.3.4
Requires-Dist: webcolors==1.13
Requires-Dist: webencodings==0.5.1
Requires-Dist: websocket-client==1.7.0
Requires-Dist: Werkzeug==3.0.2
Requires-Dist: widgetsnbextension==4.0.9
Requires-Dist: wordcloud==1.9.3
Requires-Dist: wrapt==1.16.0
Requires-Dist: xxhash==3.4.1
Requires-Dist: xyzservices==2023.10.1
Requires-Dist: yarg==0.1.9
Requires-Dist: yarl==1.9.4
Requires-Dist: zict==3.0.0
Requires-Dist: zipp==3.17.0
